matrix_supportbot/__init__.py
matrix_supportbot/main.py
matrix_supportbot/classes/__init__.py
matrix_supportbot/classes/bot.py
matrix_supportbot-0.1.2.dist-info/METADATA
matrix_supportbot-0.1.2.dist-info/WHEEL
matrix_supportbot-0.1.2.dist-info/entry_points.txt
matrix_supportbot-0.1.2.dist-info/licenses/LICENSE
matrix_supportbot-0.1.2.dist-info/RECORD
