Metadata-Version: 2.3
Name: matrix-supportbot
Version: 0.1.2
Summary: Simple support chat bot for Matrix
Project-URL: Homepage, https://git.private.coffee/PrivateCoffee/matrix-supportbot
Project-URL: Bug Tracker, https://git.private.coffee/PrivateCoffee/matrix-supportbot/issues
Author-email: "Private.coffee Team" <support@private.coffee>
License: Copyright (c) 2024 Private.coffee Team <support@private.coffee>
License-File: LICENSE
Classifier: License :: OSI Approved :: MIT License
Classifier: Operating System :: OS Independent
Classifier: Programming Language :: Python :: 3
Requires-Python: >=3.10
Requires-Dist: matrix-nio>=0.24.0
Requires-Dist: pyyaml
